Session.py
__init__.py
config.py
domains.py
endpoints/book.py
endpoints/chapter.py
endpoints/character.py
endpoints/movie.py
endpoints/quote.py
my_precious_sdk-0.0.1.dist-info/LICENSE
my_precious_sdk-0.0.1.dist-info/METADATA
my_precious_sdk-0.0.1.dist-info/WHEEL
my_precious_sdk-0.0.1.dist-info/top_level.txt
my_precious_sdk-0.0.1.dist-info/RECORD
