Metadata-Version: 2.1
Name: my-precious-sdk
Version: 0.0.1
Summary: SDK for 'The One Api'
Author-email: Bryan <BryanMartinezDev@gmail.com>
Project-URL: Homepage, https://github.com/BryanMG957/Bryan_Martinez-SDK
Classifier: Programming Language :: Python :: 3
Classifier: License :: OSI Approved :: MIT License
Classifier: Operating System :: OS Independent
Requires-Python: >=3.7
License-File: LICENSE
